odoo/addons/fields_relation_data/README.rst
odoo/addons/fields_relation_data/__init__.py
odoo/addons/fields_relation_data/__manifest__.py
odoo/addons/fields_relation_data/i18n/fields_relation_data.pot
odoo/addons/fields_relation_data/readme/CONTRIBUTORS.rst
odoo/addons/fields_relation_data/readme/CREDITS.rst
odoo/addons/fields_relation_data/readme/DESCRIPTION.rst
odoo/addons/fields_relation_data/static/description/icon.png
odoo/addons/fields_relation_data/static/description/index.html
odoo/addons/fields_relation_data/views/ir_model.xml
odoo/addons/fields_relation_data/views/ir_model_fields.xml
odoo11_addon_fields_relation_data-11.0.1.0.0.99.dev5.dist-info/METADATA
odoo11_addon_fields_relation_data-11.0.1.0.0.99.dev5.dist-info/WHEEL
odoo11_addon_fields_relation_data-11.0.1.0.0.99.dev5.dist-info/top_level.txt
odoo11_addon_fields_relation_data-11.0.1.0.0.99.dev5.dist-info/RECORD
